lazyopenai/__init__.py
lazyopenai/chat.py
lazyopenai/client.py
lazyopenai/lazy.py
lazyopenai/py.typed
lazyopenai/settings.py
lazyopenai/simple/__init__.py
lazyopenai/simple/completions.py
lazyopenai/simple/embeddings.py
lazyopenai/types/__init__.py
lazyopenai/types/basetool.py
lazyopenai/types/function.py
lazyopenai/types/message.py
lazyopenai/types/toolcall.py
lazyopenai-0.5.0.dist-info/METADATA
lazyopenai-0.5.0.dist-info/WHEEL
lazyopenai-0.5.0.dist-info/licenses/LICENSE
lazyopenai-0.5.0.dist-info/RECORD
