Metadata-Version: 2.3
Name: lazyopenai
Version: 0.5.0
Author-email: narumi <toucans-cutouts0f@icloud.com>
Requires-Python: >=3.11
Requires-Dist: loguru>=0.7.2
Requires-Dist: openai>=1.56.2
Requires-Dist: pydantic-settings>=2.6.1
Provides-Extra: langfuse
Requires-Dist: langfuse>=2.55.0; extra == 'langfuse'
